hask/Prelude.py
hask/__init__.py
hask/Control/Applicative.py
hask/Control/Monad.py
hask/Control/__init__.py
hask/Data/Char.py
hask/Data/Either.py
hask/Data/Eq.py
hask/Data/Foldable.py
hask/Data/Functor.py
hask/Data/List.py
hask/Data/Maybe.py
hask/Data/Monoid.py
hask/Data/Num.py
hask/Data/Ord.py
hask/Data/Ratio.py
hask/Data/String.py
hask/Data/Traversable.py
hask/Data/Tuple.py
hask/Data/__init__.py
hask/Python/__init__.py
hask/Python/builtins.py
hask/lang/__init__.py
hask/lang/hindley_milner.py
hask/lang/lazylist.py
hask/lang/syntax.py
hask/lang/type_system.py
hask/lang/typeclasses.py
hask3-0.1.1.dist-info/DESCRIPTION.rst
hask3-0.1.1.dist-info/METADATA
hask3-0.1.1.dist-info/RECORD
hask3-0.1.1.dist-info/WHEEL
hask3-0.1.1.dist-info/metadata.json
hask3-0.1.1.dist-info/top_level.txt
