Metadata-Version: 2.0
Name: hask3
Version: 0.1.1
Summary: Haskell language features and standard library ported to Python
Home-page: https://github.com/billpmurphy/hask
Author: Bill Murphy
Author-email: billpmurphy92@gmail.com
License: Copyright (c) 2015, Bill Murphy
Requires-Dist: xoutil (<2,>=1.9.4)
